widget_bzvisualizer/__init__.py
widget_bzvisualizer/utils.py
widget_bzvisualizer/static/widget.css
widget_bzvisualizer/static/widget.js
widget_bzvisualizer-0.2.7.dist-info/METADATA
widget_bzvisualizer-0.2.7.dist-info/WHEEL
widget_bzvisualizer-0.2.7.dist-info/licenses/LICENSE.txt
widget_bzvisualizer-0.2.7.dist-info/RECORD
