Metadata-Version: 2.3
Name: widget-bzvisualizer
Version: 0.2.7
Summary: A Jupyter widget to show the Brillouin zone of periodic crystals.
Project-URL: Home, https://www.osscar.org/
Project-URL: Source, https://github.com/osscar-org/widget-bzvisualizer
Author: The OSSCAR team
License: BSD 3-Clause License
License-File: LICENSE.txt
Keywords: anywidget,brillouin-zone,jupyter,jupyterlab,osscar,reciprocal-space,widget
Classifier: Development Status :: 5 - Production/Stable
Classifier: Framework :: Jupyter
Classifier: Framework :: Jupyter :: JupyterLab
Classifier: Programming Language :: Python
Classifier: Programming Language :: Python :: 3.9
Classifier: Programming Language :: Python :: 3.10
Classifier: Programming Language :: Python :: 3.11
Classifier: Topic :: Scientific/Engineering
Requires-Python: >=3.9
Requires-Dist: anywidget~=0.9.10
Requires-Dist: numpy~=1.21
Requires-Dist: scipy~=1.10
Requires-Dist: seekpath~=2.1
Provides-Extra: dev
Requires-Dist: ase; extra == 'dev'
Requires-Dist: bumpver>=2023.1129; extra == 'dev'
Requires-Dist: jupyterlab; extra == 'dev'
Requires-Dist: notebook; extra == 'dev'
Requires-Dist: watchfiles; extra == 'dev'
